octorest/__init__.py
octorest/client.py
octorest/sockjsclient.py
octorest/websocket.py
octorest/xhrstreaming.py
octorest/xhrstreaminggenerator.py
octorest-0.4.dist-info/LICENSE
octorest-0.4.dist-info/METADATA
octorest-0.4.dist-info/WHEEL
octorest-0.4.dist-info/top_level.txt
octorest-0.4.dist-info/RECORD
