Metadata-Version: 2.1
Name: octorest
Version: 0.4
Summary: Client library for OctoPrint REST API
Home-page: https://github.com/dougbrion/OctoRest
Author: Miro Hrončok, Jiří Makarius, Douglas Brion
Author-email: miro@hroncok.cz, meadowfrey@gmail.com, me@douglasbrion.com
License: MIT
Keywords: octoprint,3d printing
Platform: UNKNOWN
Classifier: Development Status :: 3 - Alpha
Classifier: Intended Audience :: Developers
Classifier: Intended Audience :: Manufacturing
Classifier: Intended Audience :: Science/Research
Classifier: License :: OSI Approved :: MIT License
Classifier: Operating System :: POSIX :: Linux
Classifier: Programming Language :: Python
Classifier: Programming Language :: Python :: Implementation :: CPython
Classifier: Programming Language :: Python :: Implementation :: PyPy
Classifier: Programming Language :: Python :: 3
Classifier: Programming Language :: Python :: 3 :: Only
Classifier: Programming Language :: Python :: 3.3
Classifier: Programming Language :: Python :: 3.4
Classifier: Programming Language :: Python :: 3.5
Classifier: Programming Language :: Python :: 3.6
Classifier: Programming Language :: Python :: 3.7
Classifier: Topic :: Printing
Classifier: Topic :: Software Development :: Libraries
Classifier: Topic :: System :: Networking :: Monitoring
